<?xml version="1.0" encoding="UTF-8"?>
<gresources>
    <gresource prefix="/com/vinszent/GnomeTwitch">
      <file preprocess="xml-stripblanks">ui/gt-win.ui</file>
      <file preprocess="xml-stripblanks">ui/gt-player.ui</file>
      <file preprocess="xml-stripblanks">ui/gt-item-container.ui</file>
      <file preprocess="xml-stripblanks">ui/gt-container-view.ui</file>
      <file preprocess="xml-stripblanks">ui/gt-channels-container.ui</file>
      <file preprocess="xml-stripblanks">ui/gt-channels-container-child.ui</file>
      <file preprocess="xml-stripblanks">ui/gt-vod-container-child.ui</file>
      <file preprocess="xml-stripblanks">ui/gt-browse-header-bar.ui</file>
      <file preprocess="xml-stripblanks">ui/gt-channel-header-bar.ui</file>
      <file preprocess="xml-stripblanks">ui/gt-games-container.ui</file>
      <file preprocess="xml-stripblanks">ui/gt-games-container-child.ui</file>
      <file preprocess="xml-stripblanks">ui/gt-settings-dlg.ui</file>
      <file preprocess="xml-stripblanks">ui/gt-chat.ui</file>
      <file preprocess="xml-stripblanks">ui/gt-twitch-login-dlg.ui</file>
      <file preprocess="xml-stripblanks">ui/gt-twitch-channel-info-dlg.ui</file>
      <file preprocess="xml-stripblanks">ui/gt-twitch-channel-info-panel.ui</file>
      <file preprocess="xml-stripblanks">ui/gt-error-dlg.ui</file>
      <file preprocess="xml-stripblanks">ui/app-menu.ui</file>
      <file>com.vinszent.GnomeTwitch.style.css</file>
      <file>icons/offline-cover.png</file>
      <file>icons/gt-camera-symbolic.svg</file>
      <file>icons/gt-film-symbolic.svg</file>
      <file>icons/gt-show-chat-symbolic.svg</file>
      <file>icons/gt-hide-chat-symbolic.svg</file>
    </gresource>
</gresources>
